create_csv/__init__.py
create_csv/create_csv.py
create_csv_nosferatu-0.0.2.dist-info/METADATA
create_csv_nosferatu-0.0.2.dist-info/WHEEL
create_csv_nosferatu-0.0.2.dist-info/top_level.txt
create_csv_nosferatu-0.0.2.dist-info/RECORD
